aioqbt/__init__.py
aioqbt/_compat.py
aioqbt/_decorator.py
aioqbt/_paramdict.py
aioqbt/bittorrent.py
aioqbt/chrono.py
aioqbt/client.py
aioqbt/converter.py
aioqbt/exc.py
aioqbt/mapper.py
aioqbt/py.typed
aioqbt/typing.py
aioqbt/version.py
aioqbt/api/__init__.py
aioqbt/api/app.py
aioqbt/api/auth.py
aioqbt/api/log.py
aioqbt/api/rss.py
aioqbt/api/search.py
aioqbt/api/sync.py
aioqbt/api/torrents.py
aioqbt/api/transfer.py
aioqbt/api/types.py
aioqbt-1.0.0.dist-info/LICENSE
aioqbt-1.0.0.dist-info/METADATA
aioqbt-1.0.0.dist-info/WHEEL
aioqbt-1.0.0.dist-info/top_level.txt
aioqbt-1.0.0.dist-info/RECORD
