Metadata-Version: 2.1
Name: aioqbt
Version: 1.0.0
Summary: API library for qBittorrent with asyncio
Author: Aaron Tsang
License: MIT
Project-URL: Homepage, https://github.com/tsangwpx/aioqbt
Project-URL: Documentation, https://aioqbt.readthedocs.io/en/latest/
Project-URL: Source, https://github.com/tsangwpx/aioqbt
Keywords: qbittorrent,asyncio
Classifier: Development Status :: 4 - Beta
Classifier: Framework :: AsyncIO
Classifier: License :: OSI Approved :: MIT License
Classifier: Operating System :: OS Independent
Classifier: Programming Language :: Python :: 3
Classifier: Programming Language :: Python :: 3.13
Classifier: Programming Language :: Python :: 3.12
Classifier: Programming Language :: Python :: 3.11
Classifier: Programming Language :: Python :: 3.10
Classifier: Programming Language :: Python :: 3.9
Classifier: Typing :: Typed
Requires-Python: >=3.7
License-File: LICENSE
Requires-Dist: aiohttp>=3.8.1
Requires-Dist: typing-extensions>=4.2.0
Provides-Extra: dev
Requires-Dist: mypy>=1.5.1; extra == "dev"
Requires-Dist: black>=23.9.0; extra == "dev"
Requires-Dist: isort>=5.12.0; extra == "dev"
Provides-Extra: docs
Requires-Dist: sphinx>=7.2.5; extra == "docs"
Requires-Dist: sphinx-rtd-theme>=1.3.0; extra == "docs"
Provides-Extra: test
Requires-Dist: pytest>=7.4.2; extra == "test"
Requires-Dist: pytest-asyncio>=0.21.1; extra == "test"
Requires-Dist: coverage[toml]>=6.4.4; extra == "test"
